sketch_oxide-0.1.6.dist-info/METADATA
sketch_oxide-0.1.6.dist-info/WHEEL
sketch_oxide/__init__.py
sketch_oxide/__init__.pyi
sketch_oxide/sketch_oxide.abi3.so
sketch_oxide-0.1.6.dist-info/RECORD
